nbcollate/__init__.py
nbcollate/cli.py
nbcollate/nbcollate.py
nbcollate-0.3.1.dist-info/LICENSE
nbcollate-0.3.1.dist-info/WHEEL
nbcollate-0.3.1.dist-info/METADATA
nbcollate-0.3.1.dist-info/RECORD
