Metadata-Version: 1.2
Name: nbcollate
Version: 0.3.1
Summary: Collate Jupyter classroom assignment and submission notebooks
Home-page: https://github.com/osteele/nbcollate
License: UNKNOWN
Author: Oliver Steele
Author-email: steele@osteele.com
Requires-Python: >=3.5
Classifier: Development Status :: 3 - Alpha
Classifier: Environment :: Console
Classifier: Intended Audience :: Developers
Classifier: Intended Audience :: Education
Classifier: License :: OSI Approved :: MIT License
Classifier: Programming Language :: Python
Classifier: Programming Language :: Python :: 3
Classifier: Programming Language :: Python :: 3.5
Classifier: Programming Language :: Python :: 3.6
Classifier: Topic :: Education
Requires-Dist: nbformat (~=4.4.0)
